one_key/Credential.py
one_key/PasswordManager.py
one_key/User.py
one_key/__init__.py
one_key/__main__.py
one_key/one_key.py
onekey_manager-1.0.0.dist-info/LICENSE
onekey_manager-1.0.0.dist-info/METADATA
onekey_manager-1.0.0.dist-info/WHEEL
onekey_manager-1.0.0.dist-info/entry_points.txt
onekey_manager-1.0.0.dist-info/top_level.txt
onekey_manager-1.0.0.dist-info/RECORD
