Metadata-Version: 2.1
Name: onekey_manager
Version: 1.0.0
Summary: A command line password manager
Home-page: https://github.com/hubertdang/one-key
Author: Hubert Dang
Author-email: hubertdang@gmail.com
License-File: LICENSE
